DGF/__init__.py
DGF/apps.py
DGF/combiner.py
DGF/converter.py
DGF/defaults.py
DGF/exceptions.py
DGF/fields.py
DGF/models.py
DGF/pipeline.py
DGF/registry.py
DGF/schemas.py
DGF/utils.py
DGF/utiltypes.py
DGF/auth/__init__.py
DGF/auth/_authenticator.py
DGF/auth/authenticator.py
DGF/auth/permission.py
DGF/builtins/__init__.py
DGF/builtins/authenticators.py
DGF/builtins/links.py
DGF/builtins/permissions.py
DGF/creators/__init__.py
DGF/creators/add.py
DGF/creators/change.py
DGF/creators/delete.py
DGF/creators/query.py
DGF/creators/utils.py
DGF/resolvers/__init__.py
DGF/resolvers/add.py
DGF/resolvers/change.py
DGF/resolvers/delete.py
DGF/resolvers/query.py
DGF/resolvers/utils.py
django_graphene_framework-0.0.2.dist-info/LICENSE
django_graphene_framework-0.0.2.dist-info/METADATA
django_graphene_framework-0.0.2.dist-info/WHEEL
django_graphene_framework-0.0.2.dist-info/top_level.txt
django_graphene_framework-0.0.2.dist-info/RECORD
