Metadata-Version: 2.1
Name: django-graphene-framework
Version: 0.0.2
Summary: Framework to streamline working with django and graphene
Home-page: https://github.com/LonguCodes/DGF/
Author: Maciej Łyskawiński
Author-email: lyskawinski.maciej@gmail.com
License: UNKNOWN
Platform: UNKNOWN
Classifier: Programming Language :: Python :: 3
Classifier: License :: OSI Approved :: MIT License
Classifier: Operating System :: OS Independent
Requires-Dist: django
Requires-Dist: graphene
